daml_dit_ddit/__init__.py
daml_dit_ddit/common.py
daml_dit_ddit/log.py
daml_dit_ddit/main.py
daml_dit_ddit/py.typed
daml_dit_ddit/subcommand_build.py
daml_dit_ddit/subcommand_clean.py
daml_dit_ddit/subcommand_ditversion.py
daml_dit_ddit/subcommand_genargs.py
daml_dit_ddit/subcommand_inspect.py
daml_dit_ddit/subcommand_install.py
daml_dit_ddit/subcommand_release.py
daml_dit_ddit/subcommand_run.py
daml_dit_ddit/subcommand_show.py
daml_dit_ddit/subcommand_targetname.py
daml_dit_ddit-0.7.0.dist-info/LICENSE
daml_dit_ddit-0.7.0.dist-info/METADATA
daml_dit_ddit-0.7.0.dist-info/WHEEL
daml_dit_ddit-0.7.0.dist-info/entry_points.txt
daml_dit_ddit-0.7.0.dist-info/RECORD
