Metadata-Version: 2.1
Name: daml-dit-ddit
Version: 0.7.0
Summary: Daml Hub DIT File Tool
Home-page: https://github.com/digital-asset/daml-dit-ddit
Keywords: daml,blockchain,dlt,distributed ledger,digital asset
Author: Daml Hub Team
Author-email: daml-hub-team@digitalasset.com
Requires-Python: >=3.8,<4.0
Classifier: Programming Language :: Python :: 3
Classifier: Programming Language :: Python :: 3.8
Classifier: Programming Language :: Python :: 3.9
Classifier: Programming Language :: Python :: 3.10
Classifier: Programming Language :: Python :: 3.11
Classifier: Programming Language :: Python :: 3.12
Requires-Dist: GitPython
Requires-Dist: PyGithub
Requires-Dist: dacite
Requires-Dist: daml-dit-api
Requires-Dist: dazl (>=7,<8)
Requires-Dist: pex
Requires-Dist: pyyaml
Requires-Dist: semver
Project-URL: Repository, https://github.com/digital-asset/daml-dit-ddit
